{
  "_id": "@kingjs/reflect.define-property@1.0.4",
  "_rev": "4-a2589c29fd08964eb46c2cb5fd937e73",
  "name": "@kingjs/reflect.define-property",
  "dist-tags": {
    "latest": "1.0.4"
  },
  "versions": [
    "1.0.0",
    "1.0.1",
    "1.0.2",
    "1.0.3",
    "1.0.4"
  ],
  "time": {
    "created": "2019-02-02T03:27:18.647Z",
    "1.0.0": "2019-02-02T03:27:18.862Z",
    "modified": "2019-02-08T10:23:41.526Z",
    "1.0.1": "2019-02-02T07:49:59.929Z",
    "1.0.2": "2019-02-02T22:32:52.817Z",
    "1.0.3": "2019-02-07T08:55:05.400Z",
    "1.0.4": "2019-02-08T10:23:39.067Z"
  },
  "maintainers": [
    "kingces95 <kingces95@gmail.com>"
  ],
  "description": "Extends `Reflect.defineProperty` to allow richer descriptors which can include `callback`, `extends`, and `lazy` properties. And `lazy` can be modified by `writeOnce`, `argument`, and `static`.",
  "keywords": [],
  "repository": {
    "type": "git",
    "url": "https://repository.kingjs.net/reflect/define-property"
  },
  "license": "MIT",
  "readmeFilename": "README.md",
  "_cached": false,
  "_contentLength": 0,
  "version": "1.0.4",
  "main": "index.js",
  "scripts": {
    "test": "node .test",
    "prepublishOnly": "npm test"
  },
  "dependencies": {
    "@kingjs/is": "^1.0.9",
    "@kingjs/property-descriptor.lambdize": "^1.0.2",
    "@kingjs/property-descriptor.make-lazy": "^1.0.3",
    "@kingjs/property-descriptor.target-instance-of": "^1.0.6"
  },
  "devDependencies": {
    "@kingjs/assert-theory": "^1.0.20"
  },
  "_npmVersion": "6.4.1",
  "_nodeVersion": "10.15.0",
  "_npmUser": "kingces95 <kingces95@gmail.com>",
  "dist": {
    "integrity": "sha512-fyN6CeoVFPxPZP2wSjiMJUf1ejP1taRu8XQ9DbC8NBAuvcESmPpjVvRYSfBLOGZbigH3dhjWDr0cijv9gQvFwg==",
    "shasum": "3092af1022107644a11f9390025f3a830681feb9",
    "tarball": "https://registry.npmjs.org/@kingjs/reflect.define-property/-/reflect.define-property-1.0.4.tgz",
    "fileCount": 6,
    "unpackedSize": 14436,
    "npm-signature": "-----BEGIN PGP SIGNATURE-----\r\nVersion: OpenPGP.js v3.0.4\r\nComment: https://openpgpjs.org\r\n\r\nwsFcBAEBCAAQBQJcXVirCRA9TVsSAnZWagAAD2wQAIG9wlj6UMhTfO4qVUsL\n8//FEjGejmVQlik57LckuaEO3P96M/mU8iKyF7ZKMG2ClwxeXpBvUChLPHxn\nrPoyAiHy8mlAszLc53I9RC7aJwhpvNoRijp4Ai+R23FJ0mBpzqRgMoIHcrI4\nGPxuA5opEjojMahOChnb8Uqnmvy0+6REREr9t2GS60Qo2J6rsL0hBhn8qYvD\nD6HD/7DOrJ8EL67z+98Nc4KImcyL0CXeXTho/anxloEplHjpLjLTW3yJ/CuQ\nWzZ0I2P2Un1vgIPlFsoxPNNkGyoMuogf6X6A1+f+X0muMS+yBMna0bpOE5oU\njMaZDam+++HNM+hURQ21x0WzoQ3fp1I6gyxNhFQv4VLXMOeW4Bz1xQoLiuxJ\nYITA7sDq5EG7UETYRVEnpzmaEMkrREebE0elwJ4LJfEidV1Gla1N68VjLaot\nf6cpd4BhH17GWsMOW6LtwpTHaqH960lUHBgJI4XMQiRpLwl+lQFBe/GcEzJq\nJr8qSgWDB4GQpSWmz59W3ICcIhl2r2RG+CtKm4xenHVQAMe6kAUPqQz/jwkm\nDLDW+uV2kUb4pNaF7UDgnJ3JW2mkdBFMJsJSb1batOzNQ8IIUTS6uhAIEBEU\nPmwbUAIGXJoZ+/nKfMFjFqCJRAQmx2Lp0GqyzMln5Hre2R3uf/jopFwc+eV5\nUafg\r\n=nY3Y\r\n-----END PGP SIGNATURE-----\r\n"
  },
  "directories": {},
  "_npmOperationalInternal": {
    "host": "s3://npm-registry-packages",
    "tmp": "tmp/reflect.define-property_1.0.4_1549621418973_0.5174664653231114"
  },
  "_hasShrinkwrap": false
}